gadignore/.gitignore
gadignore/__init__.py
gadignore/cli.py
gadignore-0.0.4.dist-info/LICENSE
gadignore-0.0.4.dist-info/METADATA
gadignore-0.0.4.dist-info/WHEEL
gadignore-0.0.4.dist-info/entry_points.txt
gadignore-0.0.4.dist-info/top_level.txt
gadignore-0.0.4.dist-info/RECORD
