Metadata-Version: 2.1
Name: gadignore
Version: 0.0.4
Summary: CLI tool for quickly generating a .gitignore file for Python projects
Home-page: https://github.com/AlexDemure/gadignore
Author: Alexander Grishchenko
Author-email: alexanderdemure@gmail.com
Classifier: Programming Language :: Python :: 3
Classifier: License :: OSI Approved :: MIT License
Classifier: Operating System :: OS Independent
Requires-Python: >=3.8
License-File: LICENSE
Requires-Dist: typer
